README.txt
setup.cfg
setup.py
collective/__init__.py
collective.idashboard.egg-info/PKG-INFO
collective.idashboard.egg-info/SOURCES.txt
collective.idashboard.egg-info/dependency_links.txt
collective.idashboard.egg-info/entry_points.txt
collective.idashboard.egg-info/namespace_packages.txt
collective.idashboard.egg-info/not-zip-safe
collective.idashboard.egg-info/requires.txt
collective.idashboard.egg-info/top_level.txt
collective/idashboard/__init__.py
collective/idashboard/config.py
collective/idashboard/configure.zcml
collective/idashboard/interfaces.py
collective/idashboard/migrations.py
collective/idashboard/profiles.zcml
collective/idashboard/setuphandlers.py
collective/idashboard/version.txt
collective/idashboard/browser/__init__.py
collective/idashboard/browser/configure.zcml
collective/idashboard/browser/dashboard.py
collective/idashboard/browser/recent.pt
collective/idashboard/browser/resources/idashboard.js
collective/idashboard/browser/resources/jquery.field.0.9.2/field.plugin.htm
collective/idashboard/browser/resources/jquery.field.0.9.2/jquery.field.js
collective/idashboard/browser/resources/jquery.field.0.9.2/jquery.field.min.js
collective/idashboard/browser/templates/customize_portlet.pt
collective/idashboard/browser/templates/dashboard-column.pt
collective/idashboard/browser/templates/dashboard-edit-manager.pt
collective/idashboard/browser/templates/dashboard.pt
collective/idashboard/browser/templates/dashboard_macros.pt
collective/idashboard/browser/templates/error_message.pt
collective/idashboard/browser/templates/manage-dashboard.pt
collective/idashboard/browser/templates/portlet_macros.pt
collective/idashboard/browser/templates/portlets-pageform.pt
collective/idashboard/docs/README.txt
collective/idashboard/docs/buildout.cfg
collective/idashboard/locales/af/LC_MESSAGES/collective.idashboard.po
collective/idashboard/locales/de/LC_MESSAGES/collective.idashboard.po
collective/idashboard/locales/fr/LC_MESSAGES/collective.idashboard.po
collective/idashboard/profiles/default/browserlayer.xml
collective/idashboard/profiles/default/cssregistry.xml
collective/idashboard/profiles/default/idashboard_marker.txt
collective/idashboard/profiles/default/jsregistry.xml
collective/idashboard/profiles/default/metadata.xml
collective/idashboard/profiles/default/skins.xml
collective/idashboard/profiles/uninstall/cssregistry.xml
