Metadata-Version: 1.0
Name: collective.idashboard
Version: 1.2.5
Summary: This Plone add-on product gives your dashboard features similiar to those of the iGoogle dashboard.
Home-page: http://plone.org/products/collective.idashboard
Author: JC Brand
Author-email: jc@opkode.com
License: GPL
Keywords: plone dashboard idashboard igoogle
Platform: UNKNOWN
Classifier: Framework :: Plone
Classifier: Programming Language :: Python
Classifier: Topic :: Software Development :: Libraries :: Python Modules
